setup.py
hpx_insightly.egg-info/PKG-INFO
hpx_insightly.egg-info/SOURCES.txt
hpx_insightly.egg-info/dependency_links.txt
hpx_insightly.egg-info/top_level.txt
insightly/__init__.py
insightly/insightly.py