Metadata-Version: 1.0
Name: hpx-insightly
Version: 2.2.7
Summary: A thin python wrapper around insightly api. This is a fork of insightly-python which not very active
Home-page: https://github.com/harvestport/hpx-insightly
Author: UNKNOWN
Author-email: UNKNOWN
License: UNKNOWN
Platform: UNKNOWN
